odoo/addons/web_search_with_and/README.rst
odoo/addons/web_search_with_and/__init__.py
odoo/addons/web_search_with_and/__manifest__.py
odoo/addons/web_search_with_and/data/data.xml
odoo/addons/web_search_with_and/i18n/es.po
odoo/addons/web_search_with_and/i18n/it.po
odoo/addons/web_search_with_and/i18n/pt.po
odoo/addons/web_search_with_and/i18n/web_search_with_and.pot
odoo/addons/web_search_with_and/readme/CONTRIBUTORS.rst
odoo/addons/web_search_with_and/readme/DESCRIPTION.rst
odoo/addons/web_search_with_and/readme/USAGE.rst
odoo/addons/web_search_with_and/static/description/icon.png
odoo/addons/web_search_with_and/static/description/index.html
odoo/addons/web_search_with_and/static/src/js/search.js
odoo13_addon_web_search_with_and-13.0.1.0.1.dev5.dist-info/METADATA
odoo13_addon_web_search_with_and-13.0.1.0.1.dev5.dist-info/WHEEL
odoo13_addon_web_search_with_and-13.0.1.0.1.dev5.dist-info/top_level.txt
odoo13_addon_web_search_with_and-13.0.1.0.1.dev5.dist-info/RECORD
